[
    {
        "component_name": "",
        "draw_vb": "de8daa01",
        "position_vb": "a471337a",
        "blend_vb": "",
        "texcoord_vb": "",
        "ib": "de8daa01",
        "object_indexes": [
            0
        ],
        "object_classifications": [
            "Head"
        ],
        "texture_hashes": [
            [
                [
                    "Diffuse",
                    ".dds",
                    "3f855b47"
                ],
                [
                    "LightMap",
                    ".dds",
                    "3ed0f51e"
                ],
                [
                    "MetalMap",
                    ".dds",
                    "6b32141e"
                ],
                [
                    "MetalMap",
                    ".dds",
                    "47e42a82"
                ]
            ]
        ],
        "first_vs": "1cb566f57496c6b9"
    }
]