[
    {
        "component_name": "",
        "root_vs": "653c63ba4a73ca8b",
        "draw_vb": "94e135a6",
        "position_vb": "e11f9dc0",
        "blend_vb": "b51c7ba0",
        "texcoord_vb": "3bc41103",
        "ib": "044c77fb",
        "object_indexes": [
            0
        ],
        "object_classifications": [
            "Head"
        ],
        "texture_hashes": [
            [
                [
                    "Diffuse",
                    ".dds",
                    "debe1f7d"
                ],
                [
                    "LightMap",
                    ".dds",
                    "6931c45c"
                ]
            ]
        ]
    }
]